blackbricks/__init__.py
blackbricks/blackbricks.py
blackbricks/cli.py
blackbricks/databricks_sync.py
blackbricks/files.py
blackbricks-2.2.0.dist-info/LICENSE
blackbricks-2.2.0.dist-info/METADATA
blackbricks-2.2.0.dist-info/WHEEL
blackbricks-2.2.0.dist-info/entry_points.txt
blackbricks-2.2.0.dist-info/RECORD
