Metadata-Version: 2.1
Name: blackbricks
Version: 2.2.0
Summary: Black for Databricks notebooks
Home-page: https://github.com/inspera/blackbricks
License: MIT
Keywords: automation,formatter,black,sql,yapf,autopep8,pyfmt,gofmt,rustfmt
Author: Bendik Samseth
Author-email: bendik.samseth@inspera.no
Requires-Python: >=3.8,<4.0
Classifier: Development Status :: 4 - Beta
Classifier: Environment :: Console
Classifier: Intended Audience :: Developers
Classifier: License :: OSI Approved :: MIT License
Classifier: Operating System :: OS Independent
Classifier: Programming Language :: Python
Classifier: Programming Language :: Python :: 3
Classifier: Programming Language :: Python :: 3.8
Classifier: Programming Language :: Python :: 3.9
Classifier: Programming Language :: Python :: 3.10
Classifier: Programming Language :: Python :: 3.11
Classifier: Programming Language :: Python :: 3.12
Classifier: Programming Language :: Python :: 3 :: Only
Classifier: Topic :: Software Development :: Quality Assurance
Requires-Dist: black (>=24.4.2,<25.0.0)
Requires-Dist: databricks-cli (>=0.17.3,<0.18.0)
Requires-Dist: sqlparse (>=0.4.2,<0.5.0)
Requires-Dist: typer[all] (>=0.6.1,<0.8)
Project-URL: Repository, https://github.com/inspera/blackbricks
